kapipy/__init__.py
kapipy/__version__.py
kapipy/_lazy.py
kapipy/audit_manager.py
kapipy/content_manager.py
kapipy/conversion.py
kapipy/crop_layers_manager.py
kapipy/custom_errors.py
kapipy/data_classes.py
kapipy/export.py
kapipy/gis.py
kapipy/helpers.py
kapipy/job_result.py
kapipy/session_manager.py
kapipy/table_item.py
kapipy/vector_item.py
kapipy/wfs_response.py
kapipy/wfs_utils.py
kapipy-0.4.2.dist-info/licenses/LICENSE
kapipy-0.4.2.dist-info/METADATA
kapipy-0.4.2.dist-info/WHEEL
kapipy-0.4.2.dist-info/top_level.txt
kapipy-0.4.2.dist-info/RECORD
