Metadata-Version: 2.4
Name: kapipy
Version: 0.4.2
Summary: A python client for accessing and querying geospatial open data portals.
Author-email: Paul Haakma <phaakma@gmail.com>
License: MIT
Keywords: koordinates,LINZ,geospatial,open data,API,GIS,Stats NZ,LRIS
Requires-Python: >=3.10
License-File: LICENSE
Requires-Dist: pandas>=2.0.2
Requires-Dist: tenacity>=9.0.0
Requires-Dist: httpx>=0.25.0
Requires-Dist: shapely>=2.0.5
Requires-Dist: dacite>=1.9.2
Requires-Dist: pyproj>=3.7.0
Requires-Dist: pyshp>=2.3.0
Dynamic: license-file
